MANIFEST.in
README.md
setup.py
imag3/.version
imag3/__init__.py
imag3/__main__.py
imag3.egg-info/PKG-INFO
imag3.egg-info/SOURCES.txt
imag3.egg-info/dependency_links.txt
imag3.egg-info/not-zip-safe
imag3.egg-info/requires.txt
imag3.egg-info/top_level.txt
imag3/classes/__init__.py
imag3/classes/config/__init__.py
imag3/classes/image/__init__.py
imag3/classes/utils/__init__.py