Metadata-Version: 1.0
Name: imag3
Version: 1.1.7
Summary: Some description.
Home-page: http://github.com/vandenberghinc/imag3
Author: Daan van den Bergh
Author-email: vandenberghinc.contact@gmail.com
License: MIT
Platform: UNKNOWN
